{
	"$schema": "vscode://schemas/color-theme",
	"name": "Dark (Visual Studio)",
	"colors": {
		"editor.background": "#FFFFFFFF",
		"editor.foreground": "#9F9F9FFF",
		"editor.inactiveSelectionBackground": "#E1E4E7FF",
		"editorIndentGuide.background": "#E1E1E1FF",
		"editorIndentGuide.activeBackground": "#BFBFBFFF",
		"editor.selectionHighlightBackground": "#7B92FF26",
		"list.dropBackground": "#E5E7E9FF",
		"activityBarBadge.background": "#B3E0FFFF",
		"sideBarTitle.foreground": "#A5A5A5FF",
		"input.placeholderForeground": "#AAAAAAFF",
		"menu.background": "#FFFFFFFF",
		"menu.foreground": "#A1A1A1FF",
		"statusBarItem.remoteForeground": "#000000FF",
		"statusBarItem.remoteBackground": "#80EAC6FF",
		"ports.iconRunningProcessForeground": "#6FCD6BFF",
		"sideBarSectionHeader.background": "#FFFFFF00",
		"sideBarSectionHeader.border": "#A1A1A133",
		"tab.lastPinnedBorder": "#A1A1A133",
		"list.activeSelectionIconForeground": "#000000FF"
	},
	"tokenColors": [
		{
			"scope": [
				"meta.embedded",
				"source.groovy.embedded"
			],
			"settings": {
				"foreground": "#9F9F9FFF"
			}
		},
		{
			"scope": "emphasis",
			"settings": {
				"fontStyle": "italic"
			}
		},
		{
			"scope": "strong",
			"settings": {
				"fontStyle": "bold"
			}
		},
		{
			"scope": "header",
			"settings": {
				"foreground": "#B3B3FFFF"
			}
		},
		{
			"scope": "comment",
			"settings": {
				"foreground": "#7DAC68FF"
			}
		},
		{
			"scope": "constant.language",
			"settings": {
				"foreground": "#64AEECFF"
			}
		},
		{
			"scope": [
				"constant.numeric",
				"variable.other.enummember",
				"keyword.operator.plus.exponent",
				"keyword.operator.minus.exponent"
			],
			"settings": {
				"foreground": "#5AAF2EFF"
			}
		},
		{
			"scope": "constant.regexp",
			"settings": {
				"foreground": "#7375A5FF"
			}
		},
		{
			"scope": "entity.name.tag",
			"settings": {
				"foreground": "#64AEECFF"
			}
		},
		{
			"scope": "entity.name.tag.css",
			"settings": {
				"foreground": "#130DC5FF"
			}
		},
		{
			"scope": "entity.other.attribute-name",
			"settings": {
				"foreground": "#589DFFFF"
			}
		},
		{
			"scope": [
				"entity.other.attribute-name.class.css",
				"entity.other.attribute-name.class.mixin.css",
				"entity.other.attribute-name.id.css",
				"entity.other.attribute-name.parent-selector.css",
				"entity.other.attribute-name.pseudo-class.css",
				"entity.other.attribute-name.pseudo-element.css",
				"source.css.less entity.other.attribute-name.id",
				"entity.other.attribute-name.scss"
			],
			"settings": {
				"foreground": "#130DC5FF"
			}
		},
		{
			"scope": "invalid",
			"settings": {
				"foreground": "#48C600FF"
			}
		},
		{
			"scope": "markup.underline",
			"settings": {
				"fontStyle": "underline"
			}
		},
		{
			"scope": "markup.bold",
			"settings": {
				"fontStyle": "bold",
				"foreground": "#64AEECFF"
			}
		},
		{
			"scope": "markup.heading",
			"settings": {
				"fontStyle": "bold",
				"foreground": "#64AEECFF"
			}
		},
		{
			"scope": "markup.italic",
			"settings": {
				"fontStyle": "italic"
			}
		},
		{
			"scope": "markup.strikethrough",
			"settings": {
				"fontStyle": "strikethrough"
			}
		},
		{
			"scope": "markup.inserted",
			"settings": {
				"foreground": "#5AAF2EFF"
			}
		},
		{
			"scope": "markup.deleted",
			"settings": {
				"foreground": "#2A21BDFF"
			}
		},
		{
			"scope": "markup.changed",
			"settings": {
				"foreground": "#64AEECFF"
			}
		},
		{
			"scope": "punctuation.definition.quote.begin.markdown",
			"settings": {
				"foreground": "#7DAC68FF"
			}
		},
		{
			"scope": "punctuation.definition.list.begin.markdown",
			"settings": {
				"foreground": "#6699FFFF"
			}
		},
		{
			"scope": "markup.inline.raw",
			"settings": {
				"foreground": "#2A21BDFF"
			}
		},
		{
			"name": "brackets of XML/HTML tags",
			"scope": "punctuation.definition.tag",
			"settings": {
				"foreground": "#B7B7B7FF"
			}
		},
		{
			"scope": [
				"meta.preprocessor",
				"entity.name.function.preprocessor"
			],
			"settings": {
				"foreground": "#64AEECFF"
			}
		},
		{
			"scope": "meta.preprocessor.string",
			"settings": {
				"foreground": "#2A21BDFF"
			}
		},
		{
			"scope": "meta.preprocessor.numeric",
			"settings": {
				"foreground": "#5AAF2EFF"
			}
		},
		{
			"scope": "meta.structure.dictionary.key.python",
			"settings": {
				"foreground": "#589DFFFF"
			}
		},
		{
			"scope": "meta.diff.header",
			"settings": {
				"foreground": "#64AEECFF"
			}
		},
		{
			"scope": "storage",
			"settings": {
				"foreground": "#64AEECFF"
			}
		},
		{
			"scope": "storage.type",
			"settings": {
				"foreground": "#64AEECFF"
			}
		},
		{
			"scope": [
				"storage.modifier",
				"keyword.operator.noexcept"
			],
			"settings": {
				"foreground": "#64AEECFF"
			}
		},
		{
			"scope": [
				"string",
				"meta.embedded.assembly"
			],
			"settings": {
				"foreground": "#2A21BDFF"
			}
		},
		{
			"scope": "string.tag",
			"settings": {
				"foreground": "#2A21BDFF"
			}
		},
		{
			"scope": "string.value",
			"settings": {
				"foreground": "#2A21BDFF"
			}
		},
		{
			"scope": "string.regexp",
			"settings": {
				"foreground": "#6FC11DFF"
			}
		},
		{
			"name": "String interpolation",
			"scope": [
				"punctuation.definition.template-expression.begin",
				"punctuation.definition.template-expression.end",
				"punctuation.section.embedded"
			],
			"settings": {
				"foreground": "#64AEECFF"
			}
		},
		{
			"name": "Reset JavaScript string interpolation expression",
			"scope": [
				"meta.template.expression"
			],
			"settings": {
				"foreground": "#9F9F9FFF"
			}
		},
		{
			"scope": [
				"support.type.vendored.property-name",
				"support.type.property-name",
				"variable.css",
				"variable.scss",
				"variable.other.less",
				"source.coffee.embedded"
			],
			"settings": {
				"foreground": "#589DFFFF"
			}
		},
		{
			"scope": "keyword",
			"settings": {
				"foreground": "#64AEECFF"
			}
		},
		{
			"scope": "keyword.control",
			"settings": {
				"foreground": "#64AEECFF"
			}
		},
		{
			"scope": "keyword.operator",
			"settings": {
				"foreground": "#9F9F9FFF"
			}
		},
		{
			"scope": [
				"keyword.operator.new",
				"keyword.operator.expression",
				"keyword.operator.cast",
				"keyword.operator.sizeof",
				"keyword.operator.alignof",
				"keyword.operator.typeid",
				"keyword.operator.alignas",
				"keyword.operator.instanceof",
				"keyword.operator.logical.python",
				"keyword.operator.wordlike"
			],
			"settings": {
				"foreground": "#64AEECFF"
			}
		},
		{
			"scope": "keyword.other.unit",
			"settings": {
				"foreground": "#5AAF2EFF"
			}
		},
		{
			"scope": [
				"punctuation.section.embedded.begin.php",
				"punctuation.section.embedded.end.php"
			],
			"settings": {
				"foreground": "#64AEECFF"
			}
		},
		{
			"scope": "support.function.git-rebase",
			"settings": {
				"foreground": "#589DFFFF"
			}
		},
		{
			"scope": "constant.sha.git-rebase",
			"settings": {
				"foreground": "#5AAF2EFF"
			}
		},
		{
			"name": "coloring of the Java import and package identifiers",
			"scope": [
				"storage.modifier.import.java",
				"variable.language.wildcard.java",
				"storage.modifier.package.java"
			],
			"settings": {
				"foreground": "#9F9F9FFF"
			}
		},
		{
			"name": "this.self",
			"scope": "variable.language",
			"settings": {
				"foreground": "#64AEECFF"
			}
		}
	],
	"semanticHighlighting": true,
	"semanticTokenColors": {
		"newOperator": "#9F9F9FFF",
		"stringLiteral": "#2A21BDFF",
		"customLiteral": "#9F9F9FFF",
		"numberLiteral": "#5AAF2EFF",
	}
}
